md2steam/__init__.py
md2steam/converter.py
md2steam/inline_converter.py
md2steam-1.0.1.dist-info/LICENSE
md2steam-1.0.1.dist-info/METADATA
md2steam-1.0.1.dist-info/WHEEL
md2steam-1.0.1.dist-info/top_level.txt
md2steam-1.0.1.dist-info/RECORD
