Metadata-Version: 2.1
Name: md2steam
Version: 1.0.1
Summary: Markdown to Steam BBCode converter
Home-page: https://github.com/zImpact/md2steam
Author: Andrey Kataev
Author-email: kata3v.andrey@yandex.ru
Classifier: Programming Language :: Python :: 3
Classifier: License :: OSI Approved :: MIT License
Classifier: Operating System :: OS Independent
Requires-Python: >=3.10
License-File: LICENSE
